vulgata_spacy/__init__.py
vulgata_spacy/vulgata_spacy.py
vulgata_spacy/data/clem_partial.npy
vulgata_spacy/data/clem_vulgate.csv
vulgata_spacy/data/index_map_partial.json
vulgata_spacy-0.0.1.dist-info/METADATA
vulgata_spacy-0.0.1.dist-info/WHEEL
vulgata_spacy-0.0.1.dist-info/top_level.txt
vulgata_spacy-0.0.1.dist-info/RECORD
