Metadata-Version: 2.1
Name: vulgata-spacy
Version: 0.0.1
Summary: A library for finding Vulgate references in Medieval Latin texts.
Author: WJB Mattingly
Requires-Dist: pandas (<2.0.0,>=1.0.0)
Requires-Dist: protobuf (<=3.20.0)
Requires-Dist: spacy (>=3.3.0)
Requires-Dist: gensim (>=4.2.0)
Requires-Dist: annoy (>=1.10.0)
Requires-Dist: jellyfish (>=0.8.0)
